{
  "pecho": "pecho",
  "hipertrofia": "hipertrofia",
  "espalda": "espalda",
  "intermedio": "intermedio",
  "piernas": "piernas",
  "bajar grasa": "bajar grasa",
  "fullbody": "fullbody",
  "principiante": "principiante",
  "hombros": "hombros",
  "brazos": "brazos",
  "fuerza": "fuerza",
  "core": "core",
  "avanzado": "avanzado",
  "resistencia": "resistencia",
  "rodilla": "rodilla",
  "lumbar": "lumbar",
  "hombro": "hombro",
  "codo": "codo",
  "cuello": "cuello",
  "spinning": "spinning",
  "mañana": "mañana",
  "07:00": "07:00",
  "yoga": "yoga",
  "19:30": "19:30",
  "funcional": "funcional",
  "2025-11-05": "2025-11-05",
  "18:00": "18:00",
  "hiit": "hiit",
  "20:00": "20:00",
  "pilates": "pilates",
  "2025-12-01": "2025-12-01",
  "09:00": "09:00"
}